easy_socketio/__init__.py
easy_socketio/socketio.py
easy_socketio-0.0.8.dist-info/DESCRIPTION.rst
easy_socketio-0.0.8.dist-info/METADATA
easy_socketio-0.0.8.dist-info/RECORD
easy_socketio-0.0.8.dist-info/WHEEL
easy_socketio-0.0.8.dist-info/metadata.json
easy_socketio-0.0.8.dist-info/top_level.txt
